netx/__init__.py
netx/netx.py
netx-0.4.dist-info/DESCRIPTION.rst
netx-0.4.dist-info/METADATA
netx-0.4.dist-info/metadata.json
netx-0.4.dist-info/RECORD
netx-0.4.dist-info/top_level.txt
netx-0.4.dist-info/WHEEL
tests/__init__.py
tests/test_netx.py
